gemini_srt_translator/__init__.py
gemini_srt_translator/cli.py
gemini_srt_translator/ffmpeg_utils.py
gemini_srt_translator/helpers.py
gemini_srt_translator/logger.py
gemini_srt_translator/main.py
gemini_srt_translator/utils.py
gemini_srt_translator-3.0.0.dist-info/licenses/LICENSE
gemini_srt_translator-3.0.0.dist-info/METADATA
gemini_srt_translator-3.0.0.dist-info/WHEEL
gemini_srt_translator-3.0.0.dist-info/entry_points.txt
gemini_srt_translator-3.0.0.dist-info/top_level.txt
gemini_srt_translator-3.0.0.dist-info/RECORD
