Metadata-Version: 2.4
Name: gemini-srt-translator
Version: 3.0.0
Summary: A tool for translating subtitles using Google Gemini AI
Author: Matheus Castro
License-Expression: MIT
Classifier: Development Status :: 5 - Production/Stable
Classifier: Intended Audience :: Developers
Classifier: Programming Language :: Python
Classifier: Programming Language :: Python :: 3
Classifier: Programming Language :: Python :: 3.10
Classifier: Programming Language :: Python :: 3.11
Classifier: Programming Language :: Python :: 3.12
Classifier: Programming Language :: Python :: 3.13
Classifier: Operating System :: OS Independent
Classifier: Topic :: Scientific/Engineering :: Artificial Intelligence
Classifier: Topic :: Text Processing :: Linguistic
Requires-Python: >=3.10
License-File: LICENSE
Requires-Dist: google-genai>=1.56.0
Requires-Dist: srt>=3.5.3
Requires-Dist: json-repair>=0.54.3
Requires-Dist: packaging>=25.0
Requires-Dist: pydub>=0.25.1
Requires-Dist: audioop-lts==0.2.1; python_version >= "3.13"
Dynamic: license-file
